{
  "displayName": "Database Information 4304",
  "object-identifier": {
    "$base": "ObjectIdentifier",
    "value": "dbi,4304"
  },
  "object-type": {
    "$base": "Enumerated",
    "value": "database"
  },
  "object-name": {
    "$base": "String",
    "value": "Database Information 4304"
  },
  "description": {
    "$base": "String",
    "value": "Incomplete e9 09 44 81 82 3d a0 28 c1 52 c2 03 08 04"
  },
  "present-value": {
    "$base": "Boolean",
    "value": 0
  },
  "total-db-size": {
    "$base": "Unsigned",
    "value": "130964"
  },
  "free-memory": {
    "$base": "Unsigned",
    "value": "106016"
  },
  "object-count": {
    "$base": "Unsigned",
    "value": "164"
  },
  "object-list": {
    "1": {
      "$base": "ObjectIdentifier",
      "value": "analog-input,1"
    },
    "2": {
      "$base": "ObjectIdentifier",
      "value": "analog-input,2"
    },
    "3": {
      "$base": "ObjectIdentifier",
      "value": "analog-input,3"
    },
    "4": {
      "$base": "ObjectIdentifier",
      "value": "analog-input,4"
    },
    "5": {
      "$base": "ObjectIdentifier",
      "value": "analog-input,8"
    },
    "6": {
      "$base": "ObjectIdentifier",
      "value": "analog-input,12"
    },
    "7": {
      "$base": "ObjectIdentifier",
      "value": "analog-input,13"
    },
    "8": {
      "$base": "ObjectIdentifier",
      "value": "analog-input,14"
    },
    "9": {
      "$base": "ObjectIdentifier",
      "value": "analog-output,3"
    },
    "10": {
      "$base": "ObjectIdentifier",
      "value": "analog-output,4"
    },
    "11": {
      "$base": "ObjectIdentifier",
      "value": "analog-output,5"
    },
    "12": {
      "$base": "ObjectIdentifier",
      "value": "analog-output,6"
    },
    "13": {
      "$base": "ObjectIdentifier",
      "value": "analog-output,7"
    },
    "14": {
      "$base": "ObjectIdentifier",
      "value": "analog-output,8"
    },
    "15": {
      "$base": "ObjectIdentifier",
      "value": "analog-output,9"
    },
    "16": {
      "$base": "ObjectIdentifier",
      "value": "analog-output,10"
    },
    "17": {
      "$base": "ObjectIdentifier",
      "value": "analog-output,12"
    },
    "18": {
      "$base": "ObjectIdentifier",
      "value": "analog-value,1"
    },
    "19": {
      "$base": "ObjectIdentifier",
      "value": "analog-value,2"
    },
    "20": {
      "$base": "ObjectIdentifier",
      "value": "analog-value,3"
    },
    "21": {
      "$base": "ObjectIdentifier",
      "value": "analog-value,5"
    },
    "22": {
      "$base": "ObjectIdentifier",
      "value": "analog-value,6"
    },
    "23": {
      "$base": "ObjectIdentifier",
      "value": "analog-value,7"
    },
    "24": {
      "$base": "ObjectIdentifier",
      "value": "analog-value,10"
    },
    "25": {
      "$base": "ObjectIdentifier",
      "value": "analog-value,19"
    },
    "26": {
      "$base": "ObjectIdentifier",
      "value": "analog-value,20"
    },
    "27": {
      "$base": "ObjectIdentifier",
      "value": "analog-value,22"
    },
    "28": {
      "$base": "ObjectIdentifier",
      "value": "analog-value,24"
    },
    "29": {
      "$base": "ObjectIdentifier",
      "value": "analog-value,25"
    },
    "30": {
      "$base": "ObjectIdentifier",
      "value": "analog-value,26"
    },
    "31": {
      "$base": "ObjectIdentifier",
      "value": "analog-value,27"
    },
    "32": {
      "$base": "ObjectIdentifier",
      "value": "analog-value,28"
    },
    "33": {
      "$base": "ObjectIdentifier",
      "value": "analog-value,30"
    },
    "34": {
      "$base": "ObjectIdentifier",
      "value": "analog-value,43"
    },
    "35": {
      "$base": "ObjectIdentifier",
      "value": "analog-value,44"
    },
    "36": {
      "$base": "ObjectIdentifier",
      "value": "analog-value,51"
    },
    "37": {
      "$base": "ObjectIdentifier",
      "value": "analog-value,52"
    },
    "38": {
      "$base": "ObjectIdentifier",
      "value": "analog-value,53"
    },
    "39": {
      "$base": "ObjectIdentifier",
      "value": "analog-value,54"
    },
    "40": {
      "$base": "ObjectIdentifier",
      "value": "analog-value,70"
    },
    "41": {
      "$base": "ObjectIdentifier",
      "value": "analog-value,71"
    },
    "42": {
      "$base": "ObjectIdentifier",
      "value": "analog-value,72"
    },
    "43": {
      "$base": "ObjectIdentifier",
      "value": "analog-value,73"
    },
    "44": {
      "$base": "ObjectIdentifier",
      "value": "analog-value,74"
    },
    "45": {
      "$base": "ObjectIdentifier",
      "value": "analog-value,75"
    },
    "46": {
      "$base": "ObjectIdentifier",
      "value": "analog-value,76"
    },
    "47": {
      "$base": "ObjectIdentifier",
      "value": "analog-value,77"
    },
    "48": {
      "$base": "ObjectIdentifier",
      "value": "analog-value,91"
    },
    "49": {
      "$base": "ObjectIdentifier",
      "value": "analog-value,98"
    },
    "50": {
      "$base": "ObjectIdentifier",
      "value": "binary-input,5"
    },
    "51": {
      "$base": "ObjectIdentifier",
      "value": "binary-input,6"
    },
    "52": {
      "$base": "ObjectIdentifier",
      "value": "binary-input,7"
    },
    "53": {
      "$base": "ObjectIdentifier",
      "value": "binary-input,9"
    },
    "54": {
      "$base": "ObjectIdentifier",
      "value": "binary-input,10"
    },
    "55": {
      "$base": "ObjectIdentifier",
      "value": "binary-input,11"
    },
    "56": {
      "$base": "ObjectIdentifier",
      "value": "binary-output,1"
    },
    "57": {
      "$base": "ObjectIdentifier",
      "value": "binary-output,2"
    },
    "58": {
      "$base": "ObjectIdentifier",
      "value": "binary-output,11"
    },
    "59": {
      "$base": "ObjectIdentifier",
      "value": "binary-value,2"
    },
    "60": {
      "$base": "ObjectIdentifier",
      "value": "binary-value,4"
    },
    "61": {
      "$base": "ObjectIdentifier",
      "value": "binary-value,5"
    },
    "62": {
      "$base": "ObjectIdentifier",
      "value": "binary-value,7"
    },
    "63": {
      "$base": "ObjectIdentifier",
      "value": "binary-value,50"
    },
    "64": {
      "$base": "ObjectIdentifier",
      "value": "binary-value,51"
    },
    "65": {
      "$base": "ObjectIdentifier",
      "value": "binary-value,52"
    },
    "66": {
      "$base": "ObjectIdentifier",
      "value": "binary-value,53"
    },
    "67": {
      "$base": "ObjectIdentifier",
      "value": "binary-value,60"
    },
    "68": {
      "$base": "ObjectIdentifier",
      "value": "binary-value,71"
    },
    "69": {
      "$base": "ObjectIdentifier",
      "value": "binary-value,72"
    },
    "70": {
      "$base": "ObjectIdentifier",
      "value": "binary-value,73"
    },
    "71": {
      "$base": "ObjectIdentifier",
      "value": "binary-value,74"
    },
    "72": {
      "$base": "ObjectIdentifier",
      "value": "device,4304"
    },
    "73": {
      "$base": "ObjectIdentifier",
      "value": "file,1"
    },
    "74": {
      "$base": "ObjectIdentifier",
      "value": "loop,1"
    },
    "75": {
      "$base": "ObjectIdentifier",
      "value": "loop,2"
    },
    "76": {
      "$base": "ObjectIdentifier",
      "value": "loop,3"
    },
    "77": {
      "$base": "ObjectIdentifier",
      "value": "loop,4"
    },
    "78": {
      "$base": "ObjectIdentifier",
      "value": "loop,5"
    },
    "79": {
      "$base": "ObjectIdentifier",
      "value": "loop,10"
    },
    "80": {
      "$base": "ObjectIdentifier",
      "value": "notification-class,1"
    },
    "81": {
      "$base": "ObjectIdentifier",
      "value": "notification-class,2"
    },
    "82": {
      "$base": "ObjectIdentifier",
      "value": "notification-class,3"
    },
    "83": {
      "$base": "ObjectIdentifier",
      "value": "notification-class,4"
    },
    "84": {
      "$base": "ObjectIdentifier",
      "value": "notification-class,5"
    },
    "85": {
      "$base": "ObjectIdentifier",
      "value": "notification-class,6"
    },
    "86": {
      "$base": "ObjectIdentifier",
      "value": "notification-class,7"
    },
    "87": {
      "$base": "ObjectIdentifier",
      "value": "notification-class,8"
    },
    "88": {
      "$base": "ObjectIdentifier",
      "value": "notification-class,9"
    },
    "89": {
      "$base": "ObjectIdentifier",
      "value": "multi-state-value,1"
    },
    "90": {
      "$base": "ObjectIdentifier",
      "value": "multi-state-value,98"
    },
    "91": {
      "$base": "ObjectIdentifier",
      "value": "des,1"
    },
    "92": {
      "$base": "ObjectIdentifier",
      "value": "aic,1"
    },
    "93": {
      "$base": "ObjectIdentifier",
      "value": "aic,2"
    },
    "94": {
      "$base": "ObjectIdentifier",
      "value": "aic,3"
    },
    "95": {
      "$base": "ObjectIdentifier",
      "value": "aic,5"
    },
    "96": {
      "$base": "ObjectIdentifier",
      "value": "aic,6"
    },
    "97": {
      "$base": "ObjectIdentifier",
      "value": "aic,7"
    },
    "98": {
      "$base": "ObjectIdentifier",
      "value": "aic,9"
    },
    "99": {
      "$base": "ObjectIdentifier",
      "value": "aic,10"
    },
    "100": {
      "$base": "ObjectIdentifier",
      "value": "aic,11"
    },
    "101": {
      "$base": "ObjectIdentifier",
      "value": "aic,36"
    },
    "102": {
      "$base": "ObjectIdentifier",
      "value": "aic,38"
    },
    "103": {
      "$base": "ObjectIdentifier",
      "value": "aic,39"
    },
    "104": {
      "$base": "ObjectIdentifier",
      "value": "aic,40"
    },
    "105": {
      "$base": "ObjectIdentifier",
      "value": "aic,41"
    },
    "106": {
      "$base": "ObjectIdentifier",
      "value": "aic,42"
    },
    "107": {
      "$base": "ObjectIdentifier",
      "value": "aic,43"
    },
    "108": {
      "$base": "ObjectIdentifier",
      "value": "aic,44"
    },
    "109": {
      "$base": "ObjectIdentifier",
      "value": "aic,45"
    },
    "110": {
      "$base": "ObjectIdentifier",
      "value": "aic,51"
    },
    "111": {
      "$base": "ObjectIdentifier",
      "value": "aoc,1"
    },
    "112": {
      "$base": "ObjectIdentifier",
      "value": "aoc,2"
    },
    "113": {
      "$base": "ObjectIdentifier",
      "value": "aoc,6"
    },
    "114": {
      "$base": "ObjectIdentifier",
      "value": "aoc,7"
    },
    "115": {
      "$base": "ObjectIdentifier",
      "value": "aoc,8"
    },
    "116": {
      "$base": "ObjectIdentifier",
      "value": "aoc,9"
    },
    "117": {
      "$base": "ObjectIdentifier",
      "value": "aoc,10"
    },
    "118": {
      "$base": "ObjectIdentifier",
      "value": "bdc,1"
    },
    "119": {
      "$base": "ObjectIdentifier",
      "value": "bdc,2"
    },
    "120": {
      "$base": "ObjectIdentifier",
      "value": "bdc,3"
    },
    "121": {
      "$base": "ObjectIdentifier",
      "value": "bdc,13"
    },
    "122": {
      "$base": "ObjectIdentifier",
      "value": "bdc,14"
    },
    "123": {
      "$base": "ObjectIdentifier",
      "value": "dbi,4304"
    },
    "124": {
      "$base": "ObjectIdentifier",
      "value": "mic,1"
    },
    "125": {
      "$base": "ObjectIdentifier",
      "value": "mic,4"
    },
    "126": {
      "$base": "ObjectIdentifier",
      "value": "mic,19"
    },
    "127": {
      "$base": "ObjectIdentifier",
      "value": "sua,1"
    },
    "128": {
      "$base": "ObjectIdentifier",
      "value": "net,1"
    },
    "129": {
      "$base": "ObjectIdentifier",
      "value": "lcd,101"
    },
    "130": {
      "$base": "ObjectIdentifier",
      "value": "evn,1"
    },
    "131": {
      "$base": "ObjectIdentifier",
      "value": "evn,2"
    },
    "132": {
      "$base": "ObjectIdentifier",
      "value": "evn,3"
    },
    "133": {
      "$base": "ObjectIdentifier",
      "value": "evn,4"
    },
    "134": {
      "$base": "ObjectIdentifier",
      "value": "evn,5"
    },
    "135": {
      "$base": "ObjectIdentifier",
      "value": "evn,6"
    },
    "136": {
      "$base": "ObjectIdentifier",
      "value": "evn,7"
    },
    "137": {
      "$base": "ObjectIdentifier",
      "value": "evn,8"
    },
    "138": {
      "$base": "ObjectIdentifier",
      "value": "evn,9"
    },
    "139": {
      "$base": "ObjectIdentifier",
      "value": "evn,10"
    },
    "140": {
      "$base": "ObjectIdentifier",
      "value": "eva,1"
    },
    "141": {
      "$base": "ObjectIdentifier",
      "value": "eva,2"
    },
    "142": {
      "$base": "ObjectIdentifier",
      "value": "eva,3"
    },
    "143": {
      "$base": "ObjectIdentifier",
      "value": "eva,4"
    },
    "144": {
      "$base": "ObjectIdentifier",
      "value": "eva,5"
    },
    "145": {
      "$base": "ObjectIdentifier",
      "value": "eva,6"
    },
    "146": {
      "$base": "ObjectIdentifier",
      "value": "eva,7"
    },
    "147": {
      "$base": "ObjectIdentifier",
      "value": "eva,8"
    },
    "148": {
      "$base": "ObjectIdentifier",
      "value": "eva,9"
    },
    "149": {
      "$base": "ObjectIdentifier",
      "value": "eva,10"
    },
    "150": {
      "$base": "ObjectIdentifier",
      "value": "eva,11"
    },
    "151": {
      "$base": "ObjectIdentifier",
      "value": "eva,12"
    },
    "152": {
      "$base": "ObjectIdentifier",
      "value": "eva,13"
    },
    "153": {
      "$base": "ObjectIdentifier",
      "value": "eva,14"
    },
    "154": {
      "$base": "ObjectIdentifier",
      "value": "eva,15"
    },
    "155": {
      "$base": "ObjectIdentifier",
      "value": "eva,16"
    },
    "156": {
      "$base": "ObjectIdentifier",
      "value": "eva,17"
    },
    "157": {
      "$base": "ObjectIdentifier",
      "value": "eva,18"
    },
    "158": {
      "$base": "ObjectIdentifier",
      "value": "eva,19"
    },
    "159": {
      "$base": "ObjectIdentifier",
      "value": "eva,20"
    },
    "160": {
      "$base": "ObjectIdentifier",
      "value": "evs,1"
    },
    "161": {
      "$base": "ObjectIdentifier",
      "value": "pan,1"
    },
    "162": {
      "$base": "ObjectIdentifier",
      "value": "sdl,1"
    },
    "163": {
      "$base": "ObjectIdentifier",
      "value": "sug,1"
    },
    "164": {
      "$base": "ObjectIdentifier",
      "value": "lnk,101"
    },
    "$base": "Array"
  },
  "dictionary-version": {
    "$base": "String",
    "value": "2010-9-28(2) 13:35: 8"
  },
  "time-of-last-chg": {
    "$base": "DateTime",
    "value": "2000-01-01T12:12:09.100000-07:00"
  },
  "src-user-of-last-chg": {
    "$base": "Sequence",
    "type": "0-BACnetDeviceObjectPropertyReference",
    "deviceIdentifier": {
      "$base": "ObjectIdentifier",
      "unspecifiedValue": "true"
    },
    "objectIdentifier": {
      "$base": "ObjectIdentifier",
      "unspecifiedValue": "true"
    },
    "propertyIdentifier": {
      "$base": "Enumerated",
      "value": "all",
      "type": "0-BACnetPropertyIdentifier"
    }
  },
  "src-device-of-last-chg": {
    "$base": "ObjectIdentifier",
    "unspecifiedValue": "true"
  },
  "database-revision": {
    "$base": "Unsigned",
    "value": "200"
  },
  "total-graphic-memory": {
    "$base": "Choice",
    "null": {
      "$base": "Null"
    }
  },
  "free-graphic-memory": {
    "$base": "Choice",
    "null": {
      "$base": "Null"
    }
  }
}