{
  "displayName": "RTE Fail Safe Type 4 N/O MIC",
  "object-identifier": {
    "$base": "ObjectIdentifier",
    "value": "mic,10"
  },
  "object-type": {
    "$base": "Enumerated",
    "value": "multi-state-input-configuration"
  },
  "object-name": {
    "$base": "String",
    "value": "RTE Fail Safe Type 4 N/O MIC"
  },
  "description": {
    "$base": "String",
    "value": ""
  },
  "flag": {
    "$base": "Unsigned",
    "value": 0
  },
  "state-text": {
    "1": {
      "$base": "String",
      "value": "Door Closed"
    },
    "2": {
      "$base": "String",
      "value": "Request to Exit"
    },
    "3": {
      "$base": "String",
      "value": "Trouble (shorted)"
    },
    "4": {
      "$base": "String",
      "value": "Trouble (open)"
    },
    "$base": "Array"
  },
  "voltage-range": {
    "1": {
      "$base": "Sequence",
      "lowerRange": {
        "$base": "Real",
        "value": "2.9"
      },
      "upperRange": {
        "$base": "Real",
        "value": "4.02"
      }
    },
    "2": {
      "$base": "Sequence",
      "lowerRange": {
        "$base": "Real",
        "value": "1.17"
      },
      "upperRange": {
        "$base": "Real",
        "value": "2.89"
      }
    },
    "3": {
      "$base": "Sequence",
      "lowerRange": {
        "$base": "Real",
        "value": 0
      },
      "upperRange": {
        "$base": "Real",
        "value": "1.16"
      }
    },
    "4": {
      "$base": "Sequence",
      "lowerRange": {
        "$base": "Real",
        "value": "4.03"
      },
      "upperRange": {
        "$base": "Real",
        "value": "5"
      }
    },
    "$base": "Array"
  },
  "hal-flags": {
    "$base": "BitString",
    "value": "accesscontrol"
  }
}